jaraco/financial/__init__.py
jaraco/financial/apple-card-rename.py
jaraco/financial/ledger.py
jaraco/financial/lifo.py
jaraco/financial/msmoney.py
jaraco/financial/ofx.py
jaraco/financial/paychex.py
jaraco/financial/qif.py
jaraco/financial/records.py
scripts/get-deductions.py
jaraco.financial-2.2.0.dist-info/LICENSE
jaraco.financial-2.2.0.dist-info/METADATA
jaraco.financial-2.2.0.dist-info/WHEEL
jaraco.financial-2.2.0.dist-info/entry_points.txt
jaraco.financial-2.2.0.dist-info/top_level.txt
jaraco.financial-2.2.0.dist-info/RECORD
