Metadata-Version: 2.1
Name: jaraco.financial
Version: 2.2.0
Summary: Tools and routines for managing personal finances by jaraco
Home-page: https://github.com/jaraco/jaraco.financial
Author: Jason R. Coombs
Author-email: jaraco@jaraco.com
Classifier: Development Status :: 5 - Production/Stable
Classifier: Intended Audience :: Developers
Classifier: License :: OSI Approved :: MIT License
Classifier: Programming Language :: Python :: 3
Classifier: Programming Language :: Python :: 3 :: Only
Requires-Python: >=3.8
License-File: LICENSE
Requires-Dist: keyring
Requires-Dist: path >=16.10
Requires-Dist: ofxparse
Requires-Dist: requests
Requires-Dist: jaraco.itertools
Requires-Dist: jaraco.logging
Requires-Dist: jaraco.ui
Requires-Dist: jaraco.collections
Requires-Dist: python-dateutil >=2.0
Requires-Dist: jaraco.functools
Requires-Dist: autocommand
Provides-Extra: docs
Requires-Dist: sphinx >=3.5 ; extra == 'docs'
Requires-Dist: sphinx <7.2.5 ; extra == 'docs'
Requires-Dist: jaraco.packaging >=9.3 ; extra == 'docs'
Requires-Dist: rst.linker >=1.9 ; extra == 'docs'
Requires-Dist: furo ; extra == 'docs'
Requires-Dist: sphinx-lint ; extra == 'docs'
Provides-Extra: testing
Requires-Dist: pytest >=6 ; extra == 'testing'
Requires-Dist: pytest-checkdocs >=2.4 ; extra == 'testing'
Requires-Dist: pytest-cov ; extra == 'testing'
Requires-Dist: pytest-enabler >=2.2 ; extra == 'testing'
Requires-Dist: pytest-ruff >=0.2.1 ; extra == 'testing'
Requires-Dist: splinter ; extra == 'testing'
Requires-Dist: types-python-dateutil ; extra == 'testing'
Requires-Dist: types-requests ; extra == 'testing'
Requires-Dist: types-PyYAML ; extra == 'testing'
Requires-Dist: types-six ; extra == 'testing'
Requires-Dist: pytest-mypy ; (platform_python_implementation != "PyPy") and extra == 'testing'
